MANIFEST.in
README.rst
TITLE.txt
lh-agpl3-LICENSE.txt
setup.py
./bin/gcipher
unisos/__init__.py
unisos.gcipher.egg-info/PKG-INFO
unisos.gcipher.egg-info/SOURCES.txt
unisos.gcipher.egg-info/dependency_links.txt
unisos.gcipher.egg-info/namespace_packages.txt
unisos.gcipher.egg-info/not-zip-safe
unisos.gcipher.egg-info/top_level.txt
unisos/gcipher/AutomaticClass.py
unisos/gcipher/Const.py
unisos/gcipher/GtkAttributesFacade.py
unisos/gcipher/LibGladeApplication.py
unisos/gcipher/MainCLI.py
unisos/gcipher/MainGUI.py
unisos/gcipher/Proxy.py
unisos/gcipher/__init__.py
unisos/gcipher/cipher/Caesar.py
unisos/gcipher/cipher/CharacterCipher.py
unisos/gcipher/cipher/Gie.py
unisos/gcipher/cipher/KeyedCipher.py
unisos/gcipher/cipher/Rot.py
unisos/gcipher/cipher/Tools.py
unisos/gcipher/cipher/Vigenere.py
unisos/gcipher/cipher/__init__.py
unisos/gcipher/ciphergui/Caesar.py
unisos/gcipher/ciphergui/CipherGUIList.py
unisos/gcipher/ciphergui/Gie.py
unisos/gcipher/ciphergui/KeyDialog.py
unisos/gcipher/ciphergui/Rot.py
unisos/gcipher/ciphergui/Vigenere.py
unisos/gcipher/ciphergui/__init__.py